<?xml version="1.0" encoding="UTF-8"?>
<ejb-jar xmlns:xsi="http://www.w3.org/2001/XMLSchema-instance" xmlns="http://java.sun.com/xml/ns/javaee" xmlns:ejb="http://java.sun.com/xml/ns/javaee/ejb-jar_3_0.xsd" xsi:schemaLocation="http://java.sun.com/xml/ns/javaee http://java.sun.com/xml/ns/javaee/ejb-jar_3_0.xsd" version="3.0">
  <enterprise-beans>
    <session>
      <ejb-name>BevandaSessionBean</ejb-name>
      <business-local>it.softfood.session.bevanda.BevandaSessionBeanLocal</business-local>
      <business-remote>it.softfood.session.bevanda.BevandaSessionBeanRemote</business-remote>
      <ejb-class>it.softfood.session.bevanda.BevandaSessionBean</ejb-class>
      <session-type>Stateless</session-type>
    </session>
    <session>
      <ejb-name>BevandaMagazzinoSessionBean</ejb-name>
      <business-local>it.softfood.session.bevandamagazzino.BevandaMagazzinoSessionBeanLocal</business-local>
      <business-remote>it.softfood.session.bevandamagazzino.BevandaMagazzinoSessionBeanRemote</business-remote>
      <ejb-class>it.softfood.session.bevandamagazzino.BevandaMagazzinoSessionBean</ejb-class>
      <session-type>Stateless</session-type>
    </session>
    <session>
      <ejb-name>EntrataSessionBean</ejb-name>
      <business-local>it.softfood.session.entrata.EntrataSessionBeanLocal</business-local>
      <business-remote>it.softfood.session.entrata.EntrataSessionBeanRemote</business-remote>
      <ejb-class>it.softfood.session.entrata.EntrataSessionBean</ejb-class>
      <session-type>Stateless</session-type>
    </session>
    <session>
      <ejb-name>IndirizzoSessionBean</ejb-name>
      <business-local>it.softfood.session.indirizzo.IndirizzoSessionBeanLocal</business-local>
      <business-remote>it.softfood.session.indirizzo.IndirizzoSessionBeanRemote</business-remote>
      <ejb-class>it.softfood.session.indirizzo.IndirizzoSessionBean</ejb-class>
      <session-type>Stateless</session-type>
    </session>
    <session>
      <ejb-name>IngredienteSessionBean</ejb-name>
      <business-local>it.softfood.session.ingrediente.IngredienteSessionBeanLocal</business-local>
      <business-remote>it.softfood.session.ingrediente.IngredienteSessionBeanRemote</business-remote>
      <ejb-class>it.softfood.session.ingrediente.IngredienteSessionBean</ejb-class>
      <session-type>Stateless</session-type>
    </session>
    <session>
      <ejb-name>IngredienteFrescoSessionBean</ejb-name>
      <business-local>it.softfood.session.ingredientefresco.IngredienteFrescoSessionBeanLocal</business-local>
      <business-remote>it.softfood.session.ingredientefresco.IngredienteFrescoSessionBeanRemote</business-remote>
      <ejb-class>it.softfood.session.ingredientefresco.IngredienteFrescoSessionBean</ejb-class>
      <session-type>Stateless</session-type>
    </session>
    <session>
      <ejb-name>IngredienteLungaConservazioneSessionBean</ejb-name>
      <business-local>it.softfood.session.ingredientelungaconservazione.IngredienteLungaConservazioneSessionBeanLocal</business-local>
      <business-remote>it.softfood.session.ingredientelungaconservazione.IngredienteLungaConservazioneSessionBeanRemote</business-remote>
      <ejb-class>it.softfood.session.ingredientelungaconservazione.IngredienteLungaConservazioneSessionBean</ejb-class>
      <session-type>Stateless</session-type>
    </session>
    <session>
      <ejb-name>IngredienteMagazzinoSessionBean</ejb-name>
      <business-local>it.softfood.session.ingredientemagazzino.IngredienteMagazzinoSessionBeanLocal</business-local>
      <business-remote>it.softfood.session.ingredientemagazzino.IngredienteMagazzinoSessionBeanRemote</business-remote>
      <ejb-class>it.softfood.session.ingredientemagazzino.IngredienteMagazzinoSessionBean</ejb-class>
      <session-type>Stateless</session-type>
    </session>
    <session>
      <ejb-name>IngredientePietanzaSessionBean</ejb-name>
      <business-local>it.softfood.session.ingredientepietanza.IngredientePietanzaSessionBeanLocal</business-local>
      <business-remote>it.softfood.session.ingredientepietanza.IngredientePietanzaSessionBeanRemote</business-remote>
      <ejb-class>it.softfood.session.ingredientepietanza.IngredientePietanzaSessionBean</ejb-class>
      <session-type>Stateless</session-type>
    </session>
    <session>
      <ejb-name>LineaOrdinazioneSessionBean</ejb-name>
      <business-local>it.softfood.session.lineaordinazione.LineaOrdinazioneSessionBeanLocal</business-local>
      <business-remote>it.softfood.session.lineaordinazione.LineaOrdinazioneSessionBeanRemote</business-remote>
      <ejb-class>it.softfood.session.lineaordinazione.LineaOrdinazioneSessionBean</ejb-class>
      <session-type>Stateless</session-type>
    </session>
    <session>
      <ejb-name>ListinoSessionBean</ejb-name>
      <business-local>it.softfood.session.listino.ListinoSessionBeanLocal</business-local>
      <business-remote>it.softfood.session.listino.ListinoSessionBeanRemote</business-remote>
      <ejb-class>it.softfood.session.listino.ListinoSessionBean</ejb-class>
      <session-type>Stateless</session-type>
    </session>
    <session>
      <ejb-name>MagazzinoSessionBean</ejb-name>
      <business-local>it.softfood.session.magazzino.MagazzinoSessionBeanLocal</business-local>
      <business-remote>it.softfood.session.magazzino.MagazzinoSessionBeanRemote</business-remote>
      <ejb-class>it.softfood.session.magazzino.MagazzinoSessionBean</ejb-class>
      <session-type>Stateless</session-type>
    </session>
    <session>
      <ejb-name>MenuSessionBean</ejb-name>
      <business-local>it.softfood.session.menu.MenuSessionBeanLocal</business-local>
      <business-remote>it.softfood.session.menu.MenuSessionBeanRemote</business-remote>
      <ejb-class>it.softfood.session.menu.MenuSessionBean</ejb-class>
      <session-type>Stateless</session-type>
    </session>
    <session>
      <ejb-name>OrdinazioneSessionBean</ejb-name>
      <business-local>it.softfood.session.ordinazione.OrdinazioneSessionBeanLocal</business-local>
      <business-remote>it.softfood.session.ordinazione.OrdinazioneSessionBeanRemote</business-remote>
      <ejb-class>it.softfood.session.ordinazione.OrdinazioneSessionBean</ejb-class>
      <session-type>Stateless</session-type>
    </session>
    <session>
      <ejb-name>PietanzaSessionBean</ejb-name>
      <business-local>it.softfood.session.pietanza.PietanzaSessionBeanLocal</business-local>
      <business-remote>it.softfood.session.pietanza.PietanzaSessionBeanRemote</business-remote>
      <ejb-class>it.softfood.session.pietanza.PietanzaSessionBean</ejb-class>
      <session-type>Stateless</session-type>
    </session>
    <session>
      <ejb-name>RegistroSessionBean</ejb-name>
      <business-local>it.softfood.session.registro.RegistroSessionBeanLocal</business-local>
      <business-remote>it.softfood.session.registro.RegistroSessionBeanRemote</business-remote>
      <ejb-class>it.softfood.session.registro.RegistroSessionBean</ejb-class>
      <session-type>Stateless</session-type>
    </session>
    <session>
      <ejb-name>RistoranteSessionBean</ejb-name>
      <business-local>it.softfood.session.ristorante.RistoranteSessionBeanLocal</business-local>
      <business-remote>it.softfood.session.ristorante.RistoranteSessionBeanRemote</business-remote>
      <ejb-class>it.softfood.session.ristorante.RistoranteSessionBean</ejb-class>
      <session-type>Stateless</session-type>
    </session>
    <session>
      <ejb-name>StaffSessionBean</ejb-name>
      <business-local>it.softfood.session.staff.StaffSessionBeanLocal</business-local>
      <business-remote>it.softfood.session.staff.StaffSessionBeanRemote</business-remote>
      <ejb-class>it.softfood.session.staff.StaffSessionBean</ejb-class>
      <session-type>Stateless</session-type>
    </session>
    <session>
      <ejb-name>TavoloSessionBean</ejb-name>
      <business-local>it.softfood.session.tavolo.TavoloSessionBeanLocal</business-local>
      <business-remote>it.softfood.session.tavolo.TavoloSessionBeanRemote</business-remote>
      <ejb-class>it.softfood.session.tavolo.TavoloSessionBean</ejb-class>
      <session-type>Stateless</session-type>
    </session>
    <session>
      <ejb-name>VarianteSessionBean</ejb-name>
      <business-local>it.softfood.session.variante.VarianteSessionBeanLocal</business-local>
      <business-remote>it.softfood.session.variante.VarianteSessionBeanRemote</business-remote>
      <ejb-class>it.softfood.session.variante.VarianteSessionBean</ejb-class>
      <session-type>Stateless</session-type>
    </session>
    <session>
      <ejb-name>ArticoloSessionBean</ejb-name>
      <business-local>it.softfood.session.articolo.ArticoloSessionBeanLocal</business-local>
      <business-remote>it.softfood.session.articolo.ArticoloSessionBeanRemote</business-remote>
      <ejb-class>it.softfood.session.articolo.ArticoloSessionBean</ejb-class>
      <session-type>Stateless</session-type>
    </session>
    <session>
      <ejb-name>OrdinazioneFacade</ejb-name>
      <business-local>it.softfood.facade.OrdinazioneFacadeLocal</business-local>
      <business-remote>it.softfood.facade.OrdinazioneFacadeRemote</business-remote>
      <ejb-class>it.softfood.facade.OrdinazioneFacade</ejb-class>
      <session-type>Stateless</session-type>
    </session>
  </enterprise-beans>
  <assembly-descriptor/>
</ejb-jar>